{
  "project_info": {
    "project_number": "1046304511786",
    "project_id": "zium-6081b",
    "storage_bucket": "zium-6081b.appspot.com"
  },
  "client": [
    {
      "client_info": {
        "mobilesdk_app_id": "1:1046304511786:android:5c2e33a8608756d4077053",
        "android_client_info": {
          "package_name": "com.example.zium"
        }
      },
      "oauth_client": [
        {
          "client_id": "1046304511786-l4fqptqvov7dvfu6hfbtvecud6ejeeb2.apps.googleusercontent.com",
          "client_type": 3
        }
      ],
      "api_key": [
        {
          "current_key": "AIzaSyAwPqQNasLqtLx6hEYo-4vZvH2qdp6xOp8"
        }
      ],
      "services": {
        "appinvite_service": {
          "other_platform_oauth_client": [
            {
              "client_id": "1046304511786-l4fqptqvov7dvfu6hfbtvecud6ejeeb2.apps.googleusercontent.com",
              "client_type": 3
            }
          ]
        }
      }
    }
  ],
  "configuration_version": "1"
}